fpdataviewer/__init__.py
fpdataviewer/__main__.py
fpdataviewer/cli/__init__.py
fpdataviewer/cli/config.py
fpdataviewer/cli/main.py
fpdataviewer/cli/main_convert.py
fpdataviewer/cli/main_inspect.py
fpdataviewer/cli/main_plot.py
fpdataviewer/cli/main_validate.py
fpdataviewer/cli/analysis/__init__.py
fpdataviewer/cli/analysis/analysis.py
fpdataviewer/cli/analysis/descriptors.py
fpdataviewer/cli/analysis/images.py
fpdataviewer/cli/analysis/misc.py
fpdataviewer/cli/analysis/rdfs.py
fpdataviewer/cli/plotting/__init__.py
fpdataviewer/cli/plotting/common.py
fpdataviewer/cli/plotting/plot_mpl.py
fpdataviewer/cli/plotting/plot_pdf.py
fpdataviewer/mlab/__init__.py
fpdataviewer/mlab/ase_adapter.py
fpdataviewer/mlab/mlab.py
fpdataviewer/mlab/ovito_adapter.py
fpdataviewer/mlab/parsing.py
fpdataviewer/mlab/validation.py
fpdataviewer-1.0.1.dist-info/LICENSE
fpdataviewer-1.0.1.dist-info/METADATA
fpdataviewer-1.0.1.dist-info/WHEEL
fpdataviewer-1.0.1.dist-info/entry_points.txt
fpdataviewer-1.0.1.dist-info/top_level.txt
fpdataviewer-1.0.1.dist-info/RECORD
