Metadata-Version: 2.1
Name: fpdataviewer
Version: 1.0.1
Summary: Reads first-principle molecular simulation data and graphs various statistics
Author-email: Thijmen Kuipers <t.p.w.kuipers@student.utwente.nl>
License: LGPL-3.0-only
Project-URL: Homepage, https://github.com/dynamicsolids/FPdataViewer
Keywords: vasp,descriptor,machine learning,atomic structure,materials science
Classifier: Development Status :: 4 - Beta
Classifier: License :: OSI Approved :: GNU Lesser General Public License v3 or later (LGPLv3+)
Classifier: Programming Language :: Python :: 3.8
Classifier: Programming Language :: Python :: 3.9
Classifier: Programming Language :: Python :: 3.10
Classifier: Programming Language :: Python :: 3.11
Classifier: Programming Language :: Python :: 3 :: Only
Classifier: Topic :: Scientific/Engineering
Classifier: Topic :: Scientific/Engineering :: Physics
Classifier: Topic :: Scientific/Engineering :: Visualization
Classifier: Operating System :: MacOS
Classifier: Operating System :: Unix
Requires-Python: >=3.8
License-File: LICENSE
Requires-Dist: numpy
Requires-Dist: pandas
Requires-Dist: matplotlib
Requires-Dist: seaborn
Requires-Dist: numba
Requires-Dist: scikit-learn
Requires-Dist: dscribe
Requires-Dist: ovito
Requires-Dist: pyside6
Requires-Dist: pillow
